{
  "Pedestrian Crossing": "PED_X",
  "Intersection on the Right": "INT_RIGHT",
  "No Entry": "NO_ENTRY",
  "Keep Right": "KEEP_RIGHT",
  "Crossroad": "XROAD",
  "Intersection with Minor Road": "INT_MINOR",
  "Dangerous Curve Left": "CURVE_LEFT",
  "No Left Turn": "NO_LEFT",
  "Bus Stop": "BUS_STOP",
  "Roundabout": "ROUNDABOUT",
  "No Stopping and Parking": "NO_STOP_PARK",
  "Turning Area": "TURN_AREA",
  "Lane Merge by Vehicle": "LANE_MERGE",
  "Slow Down": "SLOW",
  "No Trucks": "NO_TRUCKS",
  "Road Narrows Right": "NARROW_RIGHT",
  "Height Limit": "H_LIMIT",
  "No U-Turn": "NO_UTURN",
  "No Buses and Trucks": "NO_BUS_TRUCK",
  "No Right Turn and U-Turn": "NO_RIGHT_UTURN",
  "No Cars": "NO_CARS",
  "Road Narrows Left": "NARROW_LEFT",
  "Speed Bump Ahead": "SPEED_BUMP",
  "No Two-Wheelers": "NO_2W3W",
  "Inspection Area": "INSPECT",
  "Motorbikes Only": "MOTO_ONLY",
  "Obstacle Ahead": "OBSTACLE",
  "Children": "CHILDREN",
  "Trucks and Public Vehicles": "TRUCK_PUB",
  "No Motorbikes": "NO_MOTO",
  "Trucks Only": "TRUCK_ONLY",
  "Surveillance Camera": "CAM_AREA",
  "No Right Turn": "NO_RIGHT",
  "Dangerous Curves First Right": "CURVES_RIGHT",
  "No Semi-Trailers": "NO_SEMI",
  "No Left or Right Turn": "NO_LEFT_RIGHT",
  "No Straight and Right Turn": "NO_STRAIGHT_RIGHT",
  "Intersection on the Left": "INT_LEFT",
  "Speed Limit 50": "LIMIT_50",
  "Speed Limit 60": "LIMIT_60",
  "Speed Limit 80": "LIMIT_80",
  "Speed Limit 40": "LIMIT_40",
  "Left Turn Only": "LEFT_ONLY",
  "Actual Clearance Height": "H_CLEAR",
  "Other Danger": "DANGER",
  "One Way": "ONE_WAY",
  "No Parking": "NO_PARK",
  "No U-Turn Allowed Left": "NO_UTURN_LEFT",
  "Railway with Barrier": "RAIL_BAR",
  "No Left Turn and U-Turn": "NO_LEFT_UTURN",
  "Dangerous Curve Right": "CURVE_RIGHT",
  "Keep Right Obstacle": "KEEP_RIGHT_OBS"
}
